{
	"0" : 
	{
		"bPosX" : 0,
		"bPosY" : 0,
		"imageKey" : "GrassTile1",
		"innerPocketMonCnt" : 0,
		"nextMapName" : "TestTown2",
		"nextMapX" : 0,
		"nextMapY" : 4,
		"type" : 4
	},
	"1" : 
	{
		"bPosX" : 1,
		"bPosY" : 0,
		"imageKey" : "Tree1",
		"innerPocketMonCnt" : 0,
		"nextMapName" : "",
		"type" : 3
	},
	"10" : 
	{
		"bPosX" : 3,
		"bPosY" : 1,
		"imageKey" : "GrassTile1",
		"innerPocketMonCnt" : 0,
		"nextMapName" : "",
		"type" : 0
	},
	"11" : 
	{
		"bPosX" : 4,
		"bPosY" : 1,
		"imageKey" : "GrassTile1",
		"innerPocketMonCnt" : 0,
		"nextMapName" : "",
		"type" : 0
	},
	"12" : 
	{
		"bPosX" : 5,
		"bPosY" : 1,
		"imageKey" : "GrassTile1",
		"innerPocketMonCnt" : 0,
		"nextMapName" : "",
		"type" : 0
	},
	"13" : 
	{
		"bPosX" : 6,
		"bPosY" : 1,
		"imageKey" : "Tree1",
		"innerPocketMonCnt" : 0,
		"nextMapName" : "",
		"type" : 3
	},
	"14" : 
	{
		"bPosX" : 0,
		"bPosY" : 2,
		"imageKey" : "GrassTile1",
		"innerPocketMonCnt" : 0,
		"nextMapName" : "",
		"type" : 0
	},
	"15" : 
	{
		"bPosX" : 1,
		"bPosY" : 2,
		"imageKey" : "GrassTile1",
		"innerPocketMonCnt" : 0,
		"nextMapName" : "",
		"type" : 0
	},
	"16" : 
	{
		"bPosX" : 2,
		"bPosY" : 2,
		"imageKey" : "GrassTile1",
		"innerPocketMonCnt" : 0,
		"nextMapName" : "",
		"type" : 0
	},
	"17" : 
	{
		"bPosX" : 3,
		"bPosY" : 2,
		"imageKey" : "GrassTile1",
		"innerPocketMonCnt" : 0,
		"nextMapName" : "",
		"type" : 0
	},
	"18" : 
	{
		"bPosX" : 4,
		"bPosY" : 2,
		"imageKey" : "GrassTile1",
		"innerPocketMonCnt" : 0,
		"nextMapName" : "",
		"type" : 0
	},
	"19" : 
	{
		"bPosX" : 5,
		"bPosY" : 2,
		"imageKey" : "GrassTile1",
		"innerPocketMonCnt" : 0,
		"nextMapName" : "",
		"type" : 0
	},
	"2" : 
	{
		"bPosX" : 2,
		"bPosY" : 0,
		"imageKey" : "Tree1",
		"innerPocketMonCnt" : 0,
		"nextMapName" : "",
		"type" : 3
	},
	"20" : 
	{
		"bPosX" : 6,
		"bPosY" : 2,
		"imageKey" : "Tree1",
		"innerPocketMonCnt" : 0,
		"nextMapName" : "",
		"type" : 3
	},
	"21" : 
	{
		"bPosX" : 0,
		"bPosY" : 3,
		"imageKey" : "GrassTile1",
		"innerPocketMonCnt" : 0,
		"nextMapName" : "",
		"type" : 0
	},
	"22" : 
	{
		"bPosX" : 1,
		"bPosY" : 3,
		"imageKey" : "GrassTile1",
		"innerPocketMonCnt" : 0,
		"nextMapName" : "",
		"type" : 0
	},
	"23" : 
	{
		"bPosX" : 2,
		"bPosY" : 3,
		"imageKey" : "GrassTile1",
		"innerPocketMonCnt" : 0,
		"nextMapName" : "",
		"type" : 0
	},
	"24" : 
	{
		"bPosX" : 3,
		"bPosY" : 3,
		"imageKey" : "GrassTile1",
		"innerPocketMonCnt" : 0,
		"nextMapName" : "",
		"type" : 0
	},
	"25" : 
	{
		"bPosX" : 4,
		"bPosY" : 3,
		"imageKey" : "GrassTile1",
		"innerPocketMonCnt" : 0,
		"nextMapName" : "",
		"type" : 0
	},
	"26" : 
	{
		"bPosX" : 5,
		"bPosY" : 3,
		"imageKey" : "GrassTile1",
		"innerPocketMonCnt" : 0,
		"nextMapName" : "",
		"type" : 0
	},
	"27" : 
	{
		"bPosX" : 6,
		"bPosY" : 3,
		"imageKey" : "Tree1",
		"innerPocketMonCnt" : 0,
		"nextMapName" : "",
		"type" : 3
	},
	"28" : 
	{
		"bPosX" : 0,
		"bPosY" : 4,
		"imageKey" : "GrassTile1",
		"innerPocketMonCnt" : 0,
		"nextMapName" : "",
		"type" : 0
	},
	"29" : 
	{
		"bPosX" : 1,
		"bPosY" : 4,
		"imageKey" : "GrassTile1",
		"innerPocketMonCnt" : 0,
		"nextMapName" : "",
		"type" : 0
	},
	"3" : 
	{
		"bPosX" : 3,
		"bPosY" : 0,
		"imageKey" : "Tree1",
		"innerPocketMonCnt" : 0,
		"nextMapName" : "",
		"type" : 3
	},
	"30" : 
	{
		"bPosX" : 2,
		"bPosY" : 4,
		"imageKey" : "GrassTile1",
		"innerPocketMonCnt" : 0,
		"nextMapName" : "",
		"type" : 0
	},
	"31" : 
	{
		"bPosX" : 3,
		"bPosY" : 4,
		"imageKey" : "GrassTile1",
		"innerPocketMonCnt" : 0,
		"nextMapName" : "",
		"type" : 0
	},
	"32" : 
	{
		"bPosX" : 4,
		"bPosY" : 4,
		"imageKey" : "GrassTile1",
		"innerPocketMonCnt" : 0,
		"nextMapName" : "",
		"type" : 0
	},
	"33" : 
	{
		"bPosX" : 5,
		"bPosY" : 4,
		"imageKey" : "GrassTile1",
		"innerPocketMonCnt" : 0,
		"nextMapName" : "",
		"type" : 0
	},
	"34" : 
	{
		"bPosX" : 6,
		"bPosY" : 4,
		"imageKey" : "Tree1",
		"innerPocketMonCnt" : 0,
		"nextMapName" : "",
		"type" : 3
	},
	"35" : 
	{
		"bPosX" : 0,
		"bPosY" : 5,
		"imageKey" : "Bush1",
		"innerPocketLevel-0" : 5,
		"innerPocketMonCnt" : 1,
		"innerPocketName-0" : "Pikachu",
		"nextMapName" : "",
		"type" : 2
	},
	"36" : 
	{
		"bPosX" : 1,
		"bPosY" : 5,
		"imageKey" : "Bush1",
		"innerPocketLevel-0" : 5,
		"innerPocketMonCnt" : 1,
		"innerPocketName-0" : "Pikachu",
		"nextMapName" : "",
		"type" : 2
	},
	"37" : 
	{
		"bPosX" : 2,
		"bPosY" : 5,
		"imageKey" : "Tree1",
		"innerPocketMonCnt" : 0,
		"nextMapName" : "",
		"type" : 3
	},
	"38" : 
	{
		"bPosX" : 3,
		"bPosY" : 5,
		"imageKey" : "GrassTile1",
		"innerPocketMonCnt" : 0,
		"nextMapName" : "",
		"type" : 0
	},
	"39" : 
	{
		"bPosX" : 4,
		"bPosY" : 5,
		"imageKey" : "GrassTile1",
		"innerPocketMonCnt" : 0,
		"nextMapName" : "",
		"type" : 0
	},
	"4" : 
	{
		"bPosX" : 4,
		"bPosY" : 0,
		"imageKey" : "Tree1",
		"innerPocketMonCnt" : 0,
		"nextMapName" : "",
		"type" : 3
	},
	"40" : 
	{
		"bPosX" : 5,
		"bPosY" : 5,
		"imageKey" : "GrassTile1",
		"innerPocketMonCnt" : 0,
		"nextMapName" : "",
		"type" : 0
	},
	"41" : 
	{
		"bPosX" : 6,
		"bPosY" : 5,
		"imageKey" : "Tree1",
		"innerPocketMonCnt" : 0,
		"nextMapName" : "",
		"type" : 3
	},
	"42" : 
	{
		"bPosX" : 0,
		"bPosY" : 6,
		"imageKey" : "Bush1",
		"innerPocketLevel-0" : 5,
		"innerPocketMonCnt" : 1,
		"innerPocketName-0" : "Pikachu",
		"nextMapName" : "",
		"type" : 2
	},
	"43" : 
	{
		"bPosX" : 1,
		"bPosY" : 6,
		"imageKey" : "Bush1",
		"innerPocketLevel-0" : 5,
		"innerPocketMonCnt" : 1,
		"innerPocketName-0" : "Pikachu",
		"nextMapName" : "",
		"type" : 2
	},
	"44" : 
	{
		"bPosX" : 2,
		"bPosY" : 6,
		"imageKey" : "Tree1",
		"innerPocketMonCnt" : 0,
		"nextMapName" : "",
		"type" : 3
	},
	"45" : 
	{
		"bPosX" : 3,
		"bPosY" : 6,
		"imageKey" : "GrassTile1",
		"innerPocketMonCnt" : 0,
		"nextMapName" : "",
		"type" : 0
	},
	"46" : 
	{
		"bPosX" : 4,
		"bPosY" : 6,
		"imageKey" : "GrassTile1",
		"innerPocketMonCnt" : 0,
		"nextMapName" : "",
		"type" : 0
	},
	"47" : 
	{
		"bPosX" : 5,
		"bPosY" : 6,
		"imageKey" : "GrassTile1",
		"innerPocketMonCnt" : 0,
		"nextMapName" : "",
		"type" : 0
	},
	"48" : 
	{
		"bPosX" : 6,
		"bPosY" : 6,
		"imageKey" : "Tree1",
		"innerPocketMonCnt" : 0,
		"nextMapName" : "",
		"type" : 3
	},
	"5" : 
	{
		"bPosX" : 5,
		"bPosY" : 0,
		"imageKey" : "Tree1",
		"innerPocketMonCnt" : 0,
		"nextMapName" : "",
		"type" : 3
	},
	"6" : 
	{
		"bPosX" : 6,
		"bPosY" : 0,
		"imageKey" : "Tree1",
		"innerPocketMonCnt" : 0,
		"nextMapName" : "",
		"type" : 3
	},
	"7" : 
	{
		"bPosX" : 0,
		"bPosY" : 1,
		"imageKey" : "GrassTile1",
		"innerPocketMonCnt" : 0,
		"nextMapName" : "",
		"type" : 0
	},
	"8" : 
	{
		"bPosX" : 1,
		"bPosY" : 1,
		"imageKey" : "GrassTile1",
		"innerPocketMonCnt" : 0,
		"nextMapName" : "",
		"type" : 0
	},
	"9" : 
	{
		"bPosX" : 2,
		"bPosY" : 1,
		"imageKey" : "GrassTile1",
		"innerPocketMonCnt" : 0,
		"nextMapName" : "",
		"type" : 0
	},
	"mapHeight" : 7,
	"mapName" : "TestTown",
	"mapWidth" : 7,
	"startX" : 4,
	"startY" : 3
}